.gitignore
.pre-commit-config.yaml
.pylintrc
.readthedocs.yaml
CHANGELOG.md
CHANGELOG.md.license
CODE_OF_CONDUCT.md
LICENSE
README.rst
README.rst.license
gpio_expander.py
poetry.lock
poetry.lock.license
pyproject.toml
requirements.txt
setup.py
.github/PULL_REQUEST_TEMPLATE/adafruit_circuitpython_pr.md
.github/workflows/build.yml
.github/workflows/failure-help-text.yml
.github/workflows/release.yml
LICENSES/CC-BY-4.0.txt
LICENSES/MIT.txt
LICENSES/Unlicense.txt
circuitpython_gpio_expander.egg-info/PKG-INFO
circuitpython_gpio_expander.egg-info/SOURCES.txt
circuitpython_gpio_expander.egg-info/dependency_links.txt
circuitpython_gpio_expander.egg-info/requires.txt
circuitpython_gpio_expander.egg-info/top_level.txt
docs/api.rst
docs/api.rst.license
docs/conf.py
docs/examples.rst
docs/examples.rst.license
docs/index.rst
docs/index.rst.license
docs/requirements.txt
docs/_static/favicon.ico
docs/_static/favicon.ico.license
examples/gpio_expander_simpletest.py
tests/__init__.py
tests/conftest.py
tests/test_pca9534.py
tests/test_pca9535.py
tests/test_pca9555.py
tests/test_registry_params.py
tests/test_tca9534.py
tests/test_tca9535.py
tests/test_tca9555.py