Metadata-Version: 2.1
Name: circuitpython-gpio-expander
Version: 0.3.2
Summary: CircuitPython helper library for gpio expanders (Texas Instrument PCA95xx and TCA95xx chips).
Home-page: https://github.com/gpongelli/CircuitPython_gpio_expander.git
Author: Gabriele Pongelli
Author-email: 
License: MIT
Keywords: adafruit blinka circuitpython micropython gpio_expander gpio expander PCA9534 PCA9535 PCA9555 TCA9534 TCA9535 TCA9555
Classifier: Development Status :: 4 - Beta
Classifier: Intended Audience :: Developers
Classifier: Topic :: Software Development :: Libraries
Classifier: Topic :: System :: Hardware
Classifier: License :: OSI Approved :: MIT License
Classifier: Programming Language :: Python :: 3
License-File: LICENSE
